resultr_format/__init__.py
resultr_format-0.1.4.5.dist-info/METADATA
resultr_format-0.1.4.5.dist-info/RECORD
resultr_format-0.1.4.5.dist-info/WHEEL
resultr_format-0.1.4.5.dist-info/top_level.txt
