Metadata-Version: 2.1
Name: resultr-format
Version: 0.1.4.5
Summary: Making UCL PHAS results better
Home-page: https://github.com/haykkh/resultr
Author: Hayk Khachatryan
Author-email: hi@hayk.io
License: MIT
Platform: UNKNOWN
Classifier: Programming Language :: Python :: 3
Classifier: License :: OSI Approved :: MIT License
Classifier: Operating System :: OS Independent
Requires-Dist: inquirer (>=2.2.0)
